finitedepth/__init__.py
finitedepth/__main__.py
finitedepth/cache.py
finitedepth/coatinglayer.py
finitedepth/py.typed
finitedepth/reference.py
finitedepth/substrate.py
finitedepth/samples/coat.mp4
finitedepth/samples/coat.png
finitedepth/samples/ref.png
dipcoatimage_finitedepth-2.0.6.dist-info/LICENSE
dipcoatimage_finitedepth-2.0.6.dist-info/METADATA
dipcoatimage_finitedepth-2.0.6.dist-info/WHEEL
dipcoatimage_finitedepth-2.0.6.dist-info/entry_points.txt
dipcoatimage_finitedepth-2.0.6.dist-info/top_level.txt
dipcoatimage_finitedepth-2.0.6.dist-info/RECORD
