Metadata-Version: 2.1
Name: dipcoatimage-finitedepth
Version: 2.0.6
Summary: Image analysis for finite depth dip coating process
Author-email: Jisoo Song <jeesoo9595@snu.ac.kr>
License: BSD 2-Clause License
Project-URL: homepage, https://github.com/dipcoat-image/finitedepth
Project-URL: source, https://github.com/dipcoat-image/finitedepth
Project-URL: documentation, https://dipcoatimage-finitedepth.readthedocs.io
Classifier: Development Status :: 5 - Production/Stable
Classifier: Intended Audience :: Science/Research
Classifier: License :: OSI Approved :: BSD License
Classifier: Programming Language :: Python
Classifier: Programming Language :: Python :: 3
Classifier: Programming Language :: Python :: 3.10
Classifier: Programming Language :: Python :: 3.11
Classifier: Programming Language :: Python :: 3.12
Classifier: Programming Language :: Python :: 3 :: Only
Classifier: Topic :: Scientific/Engineering
Classifier: Topic :: Scientific/Engineering :: Physics
Classifier: Typing :: Typed
Classifier: Operating System :: OS Independent
Requires-Python: >=3.10
License-File: LICENSE
Requires-Dist: opencv-python-headless
Requires-Dist: numpy
Requires-Dist: scipy
Requires-Dist: numba
Requires-Dist: shapely >=2.0
Requires-Dist: curvesimilarities >=0.3.0a1
Requires-Dist: PyYAML
Requires-Dist: tqdm
Provides-Extra: dev
Requires-Dist: flake8 ; extra == 'dev'
Requires-Dist: flake8-docstrings ; extra == 'dev'
Requires-Dist: black ; extra == 'dev'
Requires-Dist: isort ; extra == 'dev'
Requires-Dist: docformatter ; extra == 'dev'
Requires-Dist: doc8 ; extra == 'dev'
Requires-Dist: mypy ; extra == 'dev'
Requires-Dist: types-PyYAML ; extra == 'dev'
Requires-Dist: dipcoatimage-finitedepth[doc,test] ; extra == 'dev'
Provides-Extra: doc
Requires-Dist: furo ; extra == 'doc'
Requires-Dist: sphinx ; extra == 'doc'
Requires-Dist: sphinx-autoapi <3.1.0 ; extra == 'doc'
Requires-Dist: sphinx-tabs >=3.4.5 ; extra == 'doc'
Requires-Dist: matplotlib ; extra == 'doc'
Provides-Extra: test
Requires-Dist: pytest ; extra == 'test'
